screenshots/__init__.py
screenshots-0.0.1.dist-info/LICENSE
screenshots-0.0.1.dist-info/METADATA
screenshots-0.0.1.dist-info/WHEEL
screenshots-0.0.1.dist-info/top_level.txt
screenshots-0.0.1.dist-info/RECORD
